Metadata-Version: 2.1
Name: mp-vehicle-managers
Version: 0.0.1
Summary: Django services app
Home-page: https://github.com/pmaigutyak/mp-vehicle-managers.git
Download-URL: https://github.com/pmaigutyak/mp-vehicle-managers.git/archive/0.0.1.tar.gz
Author: Paul Maigutyak
License: MIT
